{"url": "https://docs.google.com/spreadsheets/d/1jKW8tjbSD-G3POfPvteyVSQWgCuPwelEsXfO98VGc2k", "overview": [{"google_doc_url": "", "companies[4]['name']": "EQT", "companies[2]['value']": 8283812, "Total Fund Amount": 7761342119, "% Fracking": "3.319859299%", "companies[1]['name']": "BP", "companies[4]['value']": 5461288, "companies[0]['value']": 46343774, "companies[2]['name']": "Pioneer Natural Resources", "Direct Fracking Investment": 101478495, "companies[1]['value']": 32234091, "companies[3]['name']": "EOG Resources", "companies[0]['name']": "Shell", "Fracking Investment": 257665638.1, "companies[3]['value']": 6448621, "Pension Fund": "", "Indirect Fracking Investment": 156187143.1, "post_content": "", "Local Authority": ""}]}