{"data": [{"Sub-category/Classification": "", "Amount": 177433000, "\u00a3000": "177,433", "Description of Holding": "Lazard (Global Equities)"}, {"Sub-category/Classification": "", "Amount": 177637000, "\u00a3000": "177,637", "Description of Holding": "Wellington (Global Equities)"}, {"Sub-category/Classification": "", "Amount": 267994000, "\u00a3000": "267,994", "Description of Holding": "UBS (UK Equity Index)"}, {"Sub-category/Classification": "", "Amount": 203201000, "\u00a3000": "203,201", "Description of Holding": "BMO (Fixed Interest)"}, {"Sub-category/Classification": "", "Amount": 122542000, "\u00a3000": "122,542", "Description of Holding": "Threadneedle (Property)"}, {"Sub-category/Classification": "", "Amount": 81435000, "\u00a3000": "81,435", "Description of Holding": "GMO (Global Real Return)"}, {"Sub-category/Classification": "", "Amount": 53869000, "\u00a3000": "53,869", "Description of Holding": "RBC (Emerging Markets)"}, {"Sub-category/Classification": "", "Amount": 53921000, "\u00a3000": "53,921", "Description of Holding": "Invesco"}, {"Sub-category/Classification": "", "Amount": 5813000, "\u00a3000": "5,813", "Description of Holding": "Net Current Assets & Other Investments"}], "pooled": [{"Is Pooled? (Y/N)": "Y", "Amount": 267994000, "Name": "UBS (UK Equity Index)", "Category": "", "Rank": 1}, {"Is Pooled? (Y/N)": "N", "Amount": 203201000, "Name": "BMO (Fixed Interest)", "Category": "", "Rank": 2}, {"Is Pooled? (Y/N)": "Y", "Amount": 177637000, "Name": "Wellington (Global Equities)", "Category": "", "Rank": 3}, {"Is Pooled? (Y/N)": "Y", "Amount": 177433000, "Name": "Lazard (Global Equities)", "Category": "", "Rank": 4}, {"Is Pooled? (Y/N)": "N", "Amount": 122542000, "Name": "Threadneedle (Property)", "Category": "", "Rank": 5}, {"Is Pooled? (Y/N)": "3%", "Amount": 81435000, "Name": "GMO (Global Real Return)", "Category": "", "Rank": 6}, {"Is Pooled? (Y/N)": "N", "Amount": 53921000, "Name": "Invesco", "Category": "", "Rank": 7}, {"Is Pooled? (Y/N)": "Y", "Amount": 53869000, "Name": "RBC (Emerging Markets)", "Category": "", "Rank": 8}, {"Is Pooled? (Y/N)": "N", "Amount": 5813000, "Name": "Net Current Assets & Other Investments", "Category": "", "Rank": 9}, {"Is Pooled? (Y/N)": "", "Amount": "#NUM!", "Name": "#NUM!", "Category": "#NUM!", "Rank": 10}, {"Is Pooled? (Y/N)": "", "Amount": "#NUM!", "Name": "#NUM!", "Category": "#NUM!", "Rank": 11}, {"Is Pooled? (Y/N)": "", "Amount": "#NUM!", "Name": "#NUM!", "Category": "#NUM!", "Rank": 12}, {"Is Pooled? (Y/N)": "", "Amount": "#NUM!", "Name": "#NUM!", "Category": "#NUM!", "Rank": 13}, {"Is Pooled? (Y/N)": "", "Amount": "#NUM!", "Name": "#NUM!", "Category": "#NUM!", "Rank": 14}, {"Is Pooled? (Y/N)": "", "Amount": "#NUM!", "Name": "#NUM!", "Category": "#NUM!", "Rank": 15}]}